bolt_expressions/__init__.py
bolt_expressions/api.py
bolt_expressions/ast.py
bolt_expressions/ast_converter.py
bolt_expressions/casting.py
bolt_expressions/check.py
bolt_expressions/contrib/__init__.py
bolt_expressions/contrib/commands.py
bolt_expressions/exceptions.py
bolt_expressions/expose.py
bolt_expressions/literals.py
bolt_expressions/node.py
bolt_expressions/operations.py
bolt_expressions/optimizer.py
bolt_expressions/plugin.py
bolt_expressions/sources.py
bolt_expressions/typing.py
bolt_expressions/utils.py
bolt_expressions-0.19.2.dist-info/WHEEL
bolt_expressions-0.19.2.dist-info/METADATA
bolt_expressions-0.19.2.dist-info/RECORD
