Metadata-Version: 2.4
Name: bolt-expressions
Version: 0.19.2
Summary: Provides pandas-like expressions capabilities to the bolt extension of mecha
Keywords: beet,minecraft,bolt,mecha,expressions
Author: rx97, TheWii
License-Expression: MIT
Classifier: Programming Language :: Python :: 3
Classifier: Programming Language :: Python :: 3.10
Classifier: Programming Language :: Python :: 3.11
Classifier: Programming Language :: Python :: 3.12
Classifier: Programming Language :: Python :: 3.13
Requires-Dist: beet>=0.55.0
Requires-Dist: mecha>=0.59.2
Requires-Dist: nbtlib==1.12.1
Requires-Dist: bolt>=0.38
Requires-Dist: frozendict>=2.4.0,<3
Requires-Dist: bolt-control-flow>=0.2.0
Requires-Dist: rich>=13.2.0
Requires-Python: >=3.14, <4.0
Project-URL: Documentation, https://rx-modules.github.io/bolt-expressions/
Project-URL: Homepage, https://github.com/rx-modules/bolt-expressions
Project-URL: Repository, https://github.com/rx-modules/bolt-expressions
